django_q_registry/__init__.py
django_q_registry/_typing.py
django_q_registry/apps.py
django_q_registry/conf.py
django_q_registry/models.py
django_q_registry/py.typed
django_q_registry/registry.py
django_q_registry/management/__init__.py
django_q_registry/management/commands/__init__.py
django_q_registry/management/commands/setup_periodic_tasks.py
django_q_registry/migrations/0001_initial.py
django_q_registry/migrations/__init__.py
django_q_registry-0.5.0.dist-info/METADATA
django_q_registry-0.5.0.dist-info/WHEEL
django_q_registry-0.5.0.dist-info/licenses/AUTHORS.md
django_q_registry-0.5.0.dist-info/licenses/LICENSE
django_q_registry-0.5.0.dist-info/RECORD
